MANIFEST.in
README.txt
setup.py
twiimote/__init__.py
twiimote/twiimotelogo.py
twiimote/twiimotesession.py
twiimote.egg-info/PKG-INFO
twiimote.egg-info/SOURCES.txt
twiimote.egg-info/dependency_links.txt
twiimote.egg-info/entry_points.txt
twiimote.egg-info/requires.txt
twiimote.egg-info/top_level.txt