Metadata-Version: 1.1
Name: twiimote
Version: 1.7
Summary: a wiimote to twitter thingy.
Home-page: http://hakob.yt/e/twiimote
Author: Wesley Hill
Author-email: hakobyte@gmail.com
License: MIT License
Platform: Linux
Platform: Raspberry Pi
Classifier: Environment :: Console
